{
    "id": "urn:ngsi-ld:BodySoftLeanMass:id:XDMZ:15679729",
    "dateCreated": {
        "type": "DateTime",
        "value": "1982-09-12T09:16:04Z"
    },
    "dateModified": {
        "type": "DateTime",
        "value": "1997-02-13T17:35:45Z"
    },
    "source": {
        "type": "Text",
        "value": "Strong newspaper dog institut"
    },
    "name": {
        "type": "Text",
        "value": "Structure thousand town create spring new. Position police practice chair region phone city. Officer partner cell both parent."
    },
    "alternateName": {
        "type": "Text",
        "value": "Again walk civil cost for. Out still all figure want specific. Debate finally tough check. Up gas cut."
    },
    "description": {
        "type": "Text",
        "value": "Weight themselves"
    },
    "dataProvider": {
        "type": "Text",
        "value": "Me pretty stay protect participant fight. Art recognize finally key "
    },
    "owner": {
        "type": "StructuredValue",
        "value": [
            "urn:ngsi-ld:BodySoftLeanMass:items:GMHN:56339615",
            "urn:ngsi-ld:BodySoftLeanMass:items:UVXV:74830962"
        ]
    },
    "seeAlso": {
        "type": "StructuredValue",
        "value": [
            "urn:ngsi-ld:BodySoftLeanMass:items:NEJT:56397138"
        ]
    },
    "location": {
        "type": "geo:json",
        "value": {
            "type": "Point",
            "coordinates": [
                -32.9838625,
                -13.350756
            ]
        }
    },
    "address": {
        "type": "StructuredValue",
        "value": {
            "streetAddress": "Action whether hea",
            "addressLocality": "Able this happen positive dark. Cut laugh cold blood seat. Expert sea spend magazine necessary when travel evening.",
            "addressRegion": "Three join late health far save government born. Woman today conf",
            "addressCountry": "Door control different general subject situation recently. Hear where during trip matter.",
            "postalCode": "Record right reflect. Trouble move meeting.",
            "postOfficeBoxNumber": "Really physical move how onto fine to. Could hotel reach raise color property probably not. Field condition second leader.",
            "streetNr": "Positive to guess news. Quality run skill subject class.",
            "district": "Look travel material. High floor machine race foot. Receive small wall crime."
        }
    },
    "areaServed": {
        "type": "Text",
        "value": "Property of side leader quickly government. Pl"
    },
    "rt": {
        "type": "StructuredValue",
        "value": [
            "oic.r.body.slm"
        ]
    },
    "slm": {
        "type": "Number",
        "value": 342.3
    },
    "units": {
        "type": "Text",
        "value": "percent"
    },
    "range": {
        "type": "StructuredValue",
        "value": [
            906.5,
            314.9
        ]
    },
    "step": {
        "type": "Number",
        "value": 109.9
    },
    "precision": {
        "type": "Number",
        "value": 597.1
    },
    "n": {
        "type": "Text",
        "value": "Design family wa"
    },
    "if": {
        "type": "StructuredValue",
        "value": [
            "oic.if.s"
        ]
    },
    "type": "BodySoftLeanMass"
}