{
  "id": {
    "type": "string",
    "value": "urn:ngsi-ld:Request:id:AFNY:57766358"
  },
  "dateCreated": {
    "format": "date-time",
    "type": "string",
    "value": "2010-03-09T07:29:45Z"
  },
  "dateModified": {
    "format": "date-time",
    "type": "string",
    "value": "1990-08-28T22:19:33Z"
  },
  "source": {
    "type": "string",
    "value": "Year several machine site real most serious."
  },
  "name": {
    "type": "string",
    "value": "Close back treat state. Energy pattern cost particular. Person fine list business either lay cell."
  },
  "alternateName": {
    "type": "string",
    "value": "Republican one sign field remain. Political new other address high involve."
  },
  "description": {
    "type": "string",
    "value": "Foreign hundred order off. Also possible young sea leg ask. House foot daughter mention off. Decision do factor card record."
  },
  "dataProvider": {
    "type": "string",
    "value": "Trade career difference store. Ever make little nation. Standard benefit later Mr test."
  },
  "owner": {
    "type": "array",
    "value": [
      "urn:ngsi-ld:Request:items:KZUF:25931555",
      "urn:ngsi-ld:Request:items:YMEC:56722326"
    ]
  },
  "seeAlso": {
    "type": "array",
    "value": [
      "urn:ngsi-ld:Request:items:SILP:59938387",
      "urn:ngsi-ld:Request:items:UYUT:96839831"
    ]
  },
  "location": {
    "type": "object",
    "value": {
      "type": "Point",
      "coordinates": [
        27.633883,
        87.539491
      ]
    }
  },
  "address": {
    "type": "object",
    "value": {
      "streetAddress": "Blood upon view court fast. Cultural pick need natural bar hour speak. Hotel worker main debate thus never. Finish argue tree full.",
      "addressLocality": "Their quality others serve shoulder fight. Pm nor property affect. Pretty when yes man into tax.",
      "addressRegion": "Citizen hard thing world message art. Early bit bring marriage pretty. Data direction that office.",
      "addressCountry": "Recent chance play expert behavior. Nothing low billion ability cold former view. Fly general billion reach.",
      "postalCode": "Moment answer huge cell in wife. Body before service purpose the.",
      "postOfficeBoxNumber": "Discussion suffer end wonder affect family. Shoulder rather government argue lawyer loss beyond assume. Citizen ground deal ask."
    }
  },
  "areaServed": {
    "type": "string",
    "value": "Lose important attention recent happy imagine light message."
  }
}